sosopt/__init__.py
sosopt/abc.py
sosopt/conicproblem.py
sosopt/conversions.py
sosopt/exceptions.py
sosopt/semialgebraicset.py
sosopt/sosproblem.py
sosopt/typing.py
sosopt/coneconstraints/__init__.py
sosopt/coneconstraints/coneconstraint.py
sosopt/coneconstraints/equalityconstraint.py
sosopt/coneconstraints/from_.py
sosopt/coneconstraints/semidefiniteconstraint.py
sosopt/polymat/__init__.py
sosopt/polymat/from_.py
sosopt/polymat/from_.pyi
sosopt/polymat/init.py
sosopt/polymat/to.py
sosopt/polymat/operations/__init__.py
sosopt/polymat/operations/grammatrix.py
sosopt/polymat/operations/grammatrixsparse.py
sosopt/polymat/operations/grammatrixusingeqconstr.py
sosopt/polymat/operations/sosmonomialbasis.py
sosopt/polymat/operations/sosmonomialbasissparse.py
sosopt/polymat/sources/__init__.py
sosopt/polymat/sources/decisionvariableexpression.py
sosopt/polymat/sources/decisionvariableexpression.pyi
sosopt/polymat/sources/polynomialvariable.py
sosopt/polymat/sources/polynomialvariable.pyi
sosopt/polymat/symbols/__init__.py
sosopt/polymat/symbols/auxiliaryvariablesymbol.py
sosopt/polymat/symbols/conedecisionvariablesymbol.py
sosopt/polymat/symbols/decisionvariablesymbol.py
sosopt/polynomialconstraints/__init__.py
sosopt/polynomialconstraints/from_.py
sosopt/polynomialconstraints/polynomialconstraint.py
sosopt/polynomialconstraints/polynomialvariablesmixin.py
sosopt/polynomialconstraints/quadraticmoduleconstraint.py
sosopt/polynomialconstraints/sumofsqauresconstraint.py
sosopt/polynomialconstraints/zeropolynomialconstraint.py
sosopt/polynomialconstraints/constraintprimitives/__init__.py
sosopt/polynomialconstraints/constraintprimitives/anonymousvariablesmixin.py
sosopt/polynomialconstraints/constraintprimitives/decisionvariablesmixin.py
sosopt/polynomialconstraints/constraintprimitives/polynomialconstraintprimitive.py
sosopt/polynomialconstraints/constraintprimitives/sumofsquaresprimitive.py
sosopt/polynomialconstraints/constraintprimitives/zeropolynomialprimitive.py
sosopt-1.0.1.dist-info/METADATA
sosopt-1.0.1.dist-info/WHEEL
sosopt-1.0.1.dist-info/licenses/LICENSE
sosopt-1.0.1.dist-info/RECORD
