Metadata-Version: 2.4
Name: sosopt
Version: 1.0.1
Summary: SOSOpt is a library designed for solving sums-of-squares optimization problems.
Project-URL: Homepage, https://github.com/MichaelSchneeberger/sosopt
Author-email: Michael Schneeberger <michael.schneeb@hotmail.com>
License-File: LICENSE
Requires-Dist: cvxopt>=1.3.2
Requires-Dist: dataclassabc>=0.0.13
Requires-Dist: mosek>=10.2.2
Requires-Dist: numpy>=2.1.0
Requires-Dist: polymat>=0.0.8
Requires-Dist: scipy>=1.14.0
Requires-Dist: statemonad>=0.0.5
Requires-Dist: sympy>=1.13.0
